pymedphys_databases/__init__.py
pymedphys_databases/_install_requires.py
pymedphys_databases/_version.py
pymedphys_databases/delivery/__init__.py
pymedphys_databases/delivery/core.py
pymedphys_databases/msq/__init__.py
pymedphys_databases/msq/connect.py
pymedphys_databases/msq/constants.py
pymedphys_databases/msq/delivery.py
pymedphys_databases/msq/helpers.py
pymedphys_databases-0.11.0.dist-info/LICENSE-AGPL-3.0-or-later
pymedphys_databases-0.11.0.dist-info/LICENSE-Apache-2.0
pymedphys_databases-0.11.0.dist-info/METADATA
pymedphys_databases-0.11.0.dist-info/WHEEL
pymedphys_databases-0.11.0.dist-info/top_level.txt
pymedphys_databases-0.11.0.dist-info/RECORD
